dg_tm/15710.txt
dg_tm/__init__.py
dg_tm/char.csv
dg_tm/dict.txt
dg_tm/kb.txt
dg_tm/tmp.py
dg_tm/utils.py
dg_tm/word.csv
dg_tm/word_mining.py
dg_tm-1.0.0.dist-info/METADATA
dg_tm-1.0.0.dist-info/WHEEL
dg_tm-1.0.0.dist-info/top_level.txt
dg_tm-1.0.0.dist-info/RECORD
