Metadata-Version: 2.1
Name: dg-tm
Version: 1.0.0
Summary: version
Home-page: https://pypi.org/project/dg_tm
Author: huyi
Author-email: huyi@datagrand.com
Requires-Python: >=3.6.0
